{
    "uid": "7704780d-0803-43ae-b4a0-84a2f6299eb5",
    "name": "82_CatBoost",
    "preprocessing": [
        {
            "ml_task": "binary_classification",
            "params": {
                "columns_preprocessing": {},
                "target_preprocessing": [
                    "na_exclude"
                ],
                "ml_task": "binary_classification"
            }
        },
        {
            "ml_task": "binary_classification",
            "params": {
                "columns_preprocessing": {},
                "target_preprocessing": [
                    "na_exclude"
                ],
                "ml_task": "binary_classification"
            }
        },
        {
            "ml_task": "binary_classification",
            "params": {
                "columns_preprocessing": {},
                "target_preprocessing": [
                    "na_exclude"
                ],
                "ml_task": "binary_classification"
            }
        },
        {
            "ml_task": "binary_classification",
            "params": {
                "columns_preprocessing": {},
                "target_preprocessing": [
                    "na_exclude"
                ],
                "ml_task": "binary_classification"
            }
        },
        {
            "ml_task": "binary_classification",
            "params": {
                "columns_preprocessing": {},
                "target_preprocessing": [
                    "na_exclude"
                ],
                "ml_task": "binary_classification"
            }
        },
        {
            "ml_task": "binary_classification",
            "params": {
                "columns_preprocessing": {},
                "target_preprocessing": [
                    "na_exclude"
                ],
                "ml_task": "binary_classification"
            }
        },
        {
            "ml_task": "binary_classification",
            "params": {
                "columns_preprocessing": {},
                "target_preprocessing": [
                    "na_exclude"
                ],
                "ml_task": "binary_classification"
            }
        },
        {
            "ml_task": "binary_classification",
            "params": {
                "columns_preprocessing": {},
                "target_preprocessing": [
                    "na_exclude"
                ],
                "ml_task": "binary_classification"
            }
        },
        {
            "ml_task": "binary_classification",
            "params": {
                "columns_preprocessing": {},
                "target_preprocessing": [
                    "na_exclude"
                ],
                "ml_task": "binary_classification"
            }
        },
        {
            "ml_task": "binary_classification",
            "params": {
                "columns_preprocessing": {},
                "target_preprocessing": [
                    "na_exclude"
                ],
                "ml_task": "binary_classification"
            }
        }
    ],
    "learners": [
        {
            "library_version": "1.2.5",
            "algorithm_name": "CatBoost",
            "algorithm_short_name": "CatBoost",
            "uid": "0c2fed5d-6a3d-4414-8d98-eb1730c4358b",
            "params": {
                "model_type": "CatBoost",
                "ml_task": "binary_classification",
                "n_jobs": -1,
                "seed": 1236,
                "learning_rate": 0.1,
                "depth": 9,
                "rsm": 1.0,
                "loss_function": "Logloss",
                "eval_metric": "F1",
                "explain_level": 1
            },
            "name": "learner_fold_0",
            "best_ntree_limit": 273
        },
        {
            "library_version": "1.2.5",
            "algorithm_name": "CatBoost",
            "algorithm_short_name": "CatBoost",
            "uid": "c0d5bee4-2851-42b0-918e-0ede1f1af176",
            "params": {
                "model_type": "CatBoost",
                "ml_task": "binary_classification",
                "n_jobs": -1,
                "seed": 1236,
                "learning_rate": 0.1,
                "depth": 9,
                "rsm": 1.0,
                "loss_function": "Logloss",
                "eval_metric": "F1",
                "explain_level": 1
            },
            "name": "learner_fold_1",
            "best_ntree_limit": 136
        },
        {
            "library_version": "1.2.5",
            "algorithm_name": "CatBoost",
            "algorithm_short_name": "CatBoost",
            "uid": "4e0822de-02a3-4ca3-a747-0cb7f98d6271",
            "params": {
                "model_type": "CatBoost",
                "ml_task": "binary_classification",
                "n_jobs": -1,
                "seed": 1236,
                "learning_rate": 0.1,
                "depth": 9,
                "rsm": 1.0,
                "loss_function": "Logloss",
                "eval_metric": "F1",
                "explain_level": 1
            },
            "name": "learner_fold_2",
            "best_ntree_limit": 36
        },
        {
            "library_version": "1.2.5",
            "algorithm_name": "CatBoost",
            "algorithm_short_name": "CatBoost",
            "uid": "7f04993d-12c4-40e0-b506-f09e7759cf44",
            "params": {
                "model_type": "CatBoost",
                "ml_task": "binary_classification",
                "n_jobs": -1,
                "seed": 1236,
                "learning_rate": 0.1,
                "depth": 9,
                "rsm": 1.0,
                "loss_function": "Logloss",
                "eval_metric": "F1",
                "explain_level": 1
            },
            "name": "learner_fold_3",
            "best_ntree_limit": 33
        },
        {
            "library_version": "1.2.5",
            "algorithm_name": "CatBoost",
            "algorithm_short_name": "CatBoost",
            "uid": "a73b026d-e188-4551-ae26-08ee71eee1c0",
            "params": {
                "model_type": "CatBoost",
                "ml_task": "binary_classification",
                "n_jobs": -1,
                "seed": 1236,
                "learning_rate": 0.1,
                "depth": 9,
                "rsm": 1.0,
                "loss_function": "Logloss",
                "eval_metric": "F1",
                "explain_level": 1
            },
            "name": "learner_fold_4",
            "best_ntree_limit": 49
        },
        {
            "library_version": "1.2.5",
            "algorithm_name": "CatBoost",
            "algorithm_short_name": "CatBoost",
            "uid": "f386c62c-06ac-4e50-a523-3f0556d612a2",
            "params": {
                "model_type": "CatBoost",
                "ml_task": "binary_classification",
                "n_jobs": -1,
                "seed": 1236,
                "learning_rate": 0.1,
                "depth": 9,
                "rsm": 1.0,
                "loss_function": "Logloss",
                "eval_metric": "F1",
                "explain_level": 1
            },
            "name": "learner_fold_5",
            "best_ntree_limit": 71
        },
        {
            "library_version": "1.2.5",
            "algorithm_name": "CatBoost",
            "algorithm_short_name": "CatBoost",
            "uid": "ba7195a3-7bce-4e8b-a5c7-0a740c96594d",
            "params": {
                "model_type": "CatBoost",
                "ml_task": "binary_classification",
                "n_jobs": -1,
                "seed": 1236,
                "learning_rate": 0.1,
                "depth": 9,
                "rsm": 1.0,
                "loss_function": "Logloss",
                "eval_metric": "F1",
                "explain_level": 1
            },
            "name": "learner_fold_6",
            "best_ntree_limit": 118
        },
        {
            "library_version": "1.2.5",
            "algorithm_name": "CatBoost",
            "algorithm_short_name": "CatBoost",
            "uid": "0ff9bb3d-f59e-403d-9f72-2670a999efa8",
            "params": {
                "model_type": "CatBoost",
                "ml_task": "binary_classification",
                "n_jobs": -1,
                "seed": 1236,
                "learning_rate": 0.1,
                "depth": 9,
                "rsm": 1.0,
                "loss_function": "Logloss",
                "eval_metric": "F1",
                "explain_level": 1
            },
            "name": "learner_fold_7",
            "best_ntree_limit": 295
        },
        {
            "library_version": "1.2.5",
            "algorithm_name": "CatBoost",
            "algorithm_short_name": "CatBoost",
            "uid": "ed4404c3-428c-42c0-bb50-5dc7745d2d6b",
            "params": {
                "model_type": "CatBoost",
                "ml_task": "binary_classification",
                "n_jobs": -1,
                "seed": 1236,
                "learning_rate": 0.1,
                "depth": 9,
                "rsm": 1.0,
                "loss_function": "Logloss",
                "eval_metric": "F1",
                "explain_level": 1
            },
            "name": "learner_fold_8",
            "best_ntree_limit": 327
        },
        {
            "library_version": "1.2.5",
            "algorithm_name": "CatBoost",
            "algorithm_short_name": "CatBoost",
            "uid": "52af4ed6-5f79-4a61-9cea-44d29adab03f",
            "params": {
                "model_type": "CatBoost",
                "ml_task": "binary_classification",
                "n_jobs": -1,
                "seed": 1236,
                "learning_rate": 0.1,
                "depth": 9,
                "rsm": 1.0,
                "loss_function": "Logloss",
                "eval_metric": "F1",
                "explain_level": 1
            },
            "name": "learner_fold_9",
            "best_ntree_limit": 169
        }
    ],
    "params": {
        "additional": {
            "max_rounds": 10000,
            "early_stopping_rounds": 50,
            "max_rows_limit": null,
            "max_cols_limit": null
        },
        "preprocessing": {
            "columns_preprocessing": {},
            "target_preprocessing": [
                "na_exclude"
            ],
            "ml_task": "binary_classification"
        },
        "validation_strategy": {
            "validation_type": "kfold",
            "k_folds": 10,
            "shuffle": true,
            "stratify": true,
            "random_seed": 12,
            "X_path": "../experiments/3_Compete_mode/X.data",
            "y_path": "../experiments/3_Compete_mode/y.data",
            "results_path": "../experiments/3_Compete_mode"
        },
        "learner": {
            "model_type": "CatBoost",
            "ml_task": "binary_classification",
            "n_jobs": -1,
            "seed": 1236,
            "learning_rate": 0.1,
            "depth": 9,
            "rsm": 1.0,
            "loss_function": "Logloss",
            "eval_metric": "F1",
            "explain_level": 1
        },
        "automl_random_state": 1234,
        "ml_task": "binary_classification",
        "explain_level": 1,
        "name": "82_CatBoost",
        "status": "initialized",
        "final_loss": null,
        "train_time": null,
        "data_type": "original",
        "max_time_for_learner": 60
    },
    "saved": [
        "82_CatBoost/learner_fold_0.catboost",
        "82_CatBoost/learner_fold_1.catboost",
        "82_CatBoost/learner_fold_2.catboost",
        "82_CatBoost/learner_fold_3.catboost",
        "82_CatBoost/learner_fold_4.catboost",
        "82_CatBoost/learner_fold_5.catboost",
        "82_CatBoost/learner_fold_6.catboost",
        "82_CatBoost/learner_fold_7.catboost",
        "82_CatBoost/learner_fold_8.catboost",
        "82_CatBoost/learner_fold_9.catboost"
    ],
    "predictions_fname": "82_CatBoost/predictions_out_of_folds.csv",
    "metric_name": "f1",
    "final_loss": "-0.8554519899393401",
    "train_time": 17.578937768936157,
    "is_stacked": false,
    "joblib_version": "1.4.2",
    "threshold": 0.5017149730887855
}